sisense/__init__.py
sisense/api.py
sisense/cli.py
sisense/exception.py
sisense/resource.py
sisense/sisense_client.py
sisense/utils.py
sisense/admin/__init__.py
sisense/admin/grafana.py
sisense/admin/group.py
sisense/admin/user.py
sisense/admin/auth/__init__.py
sisense/admin/auth/auth.py
sisense/admin/auth/auth_model.py
sisense/admin/auth/oauth.py
sisense/analysis/__init__.py
sisense/analysis/dashboard.py
sisense/analysis/folder.py
sisense/analysis/widget.py
sisense/data/__init__.py
sisense/data/build.py
sisense/data/connection.py
sisense/data/datamodel.py
sisense/data/datasecurity.py
sisense/data/datasource.py
sisense/data/elasticube.py
sisense/data/hierarchy.py
sisense/data/permission.py
tests/__init__.py
tests/build.py
tests/connection.py
tests/dashboard.py
tests/datamodel.py
tests/datasecurity.py
tests/elasticube.py
tests/folder.py
tests/group.py
tests/hierarchy.py
tests/permission.py
tests/sisense_client.py
tests/test_case.py
tests/user.py
sisense-0.2.2.dist-info/LICENSE
sisense-0.2.2.dist-info/METADATA
sisense-0.2.2.dist-info/WHEEL
sisense-0.2.2.dist-info/top_level.txt
sisense-0.2.2.dist-info/RECORD
