Metadata-Version: 2.1
Name: sisense
Version: 0.2.2
Summary: Sisense API interface in Python.
Home-page: https://github.com/Bluemetrics/sisense
Author: Bluemetrics
Author-email: equipe@bluemetrics.com.br
License: UNKNOWN
Platform: UNKNOWN
Classifier: Programming Language :: Python :: 3
Classifier: License :: OSI Approved :: MIT License
Classifier: Operating System :: OS Independent
Requires-Python: >=3.7
License-File: LICENSE
